mit_d3m/__init__.py
mit_d3m/config.py
mit_d3m/dataset.py
mit_d3m/db.py
mit_d3m/loaders.py
mit_d3m/metrics.py
mit_d3m/stats.py
mit_d3m/utils.py
mit_d3m-0.2.1.dist-info/AUTHORS.rst
mit_d3m-0.2.1.dist-info/LICENSE
mit_d3m-0.2.1.dist-info/METADATA
mit_d3m-0.2.1.dist-info/WHEEL
mit_d3m-0.2.1.dist-info/top_level.txt
mit_d3m-0.2.1.dist-info/RECORD
