Metadata-Version: 2.1
Name: mit-d3m
Version: 0.2.1
Summary: MIT tools to work with D3M datasets.
Home-page: https://github.com/HDI-Project/mit-d3m
Author: MIT Data To AI Lab
Author-email: dailabmit@gmail.com
License: MIT license
Keywords: mit-d3m
Platform: UNKNOWN
Classifier: Development Status :: 3 - Alpha
Classifier: Intended Audience :: Developers
Classifier: License :: OSI Approved :: MIT License
Classifier: Natural Language :: English
Classifier: Programming Language :: Python :: 3
Classifier: Programming Language :: Python :: 3.5
Classifier: Programming Language :: Python :: 3.6
Classifier: Programming Language :: Python :: 3.7
Classifier: Topic :: Scientific/Engineering :: Artificial Intelligence
Requires-Python: >=3.5
Requires-Dist: boto3 (>=1.9.27)
Requires-Dist: funcy (>=1.11)
Requires-Dist: keras (>=2.2.4)
Requires-Dist: networkx (>=2.1)
Requires-Dist: numpy (>=1.15.2)
Requires-Dist: pandas (>=0.23.4)
Requires-Dist: psutil (>=5.4.8)
Requires-Dist: pymongo (>=3.7.2)
Requires-Dist: scikit-learn (>=0.20.0)
Requires-Dist: python-dateutil (<2.8.1,>=2.1)
Provides-Extra: dev
Requires-Dist: bumpversion (>=0.5.3) ; extra == 'dev'
Requires-Dist: pip (>=10.0.0) ; extra == 'dev'
Requires-Dist: watchdog (>=0.8.3) ; extra == 'dev'
Requires-Dist: m2r (>=0.2.0) ; extra == 'dev'
Requires-Dist: Sphinx (>=1.7.1) ; extra == 'dev'
Requires-Dist: sphinx-rtd-theme (>=0.2.4) ; extra == 'dev'
Requires-Dist: autodocsumm (>=0.1.10) ; extra == 'dev'
Requires-Dist: flake8 (>=3.5.0) ; extra == 'dev'
Requires-Dist: isort (>=4.3.4) ; extra == 'dev'
Requires-Dist: autoflake (>=1.1) ; extra == 'dev'
Requires-Dist: autopep8 (>=1.3.5) ; extra == 'dev'
Requires-Dist: twine (>=1.10.0) ; extra == 'dev'
Requires-Dist: wheel (>=0.30.0) ; extra == 'dev'
Requires-Dist: tox (>=2.9.1) ; extra == 'dev'
Requires-Dist: coverage (>=4.5.1) ; extra == 'dev'
Requires-Dist: pytest (>=3.4.2) ; extra == 'dev'
Requires-Dist: pytest-cov (>=2.6.0) ; extra == 'dev'
Provides-Extra: test
Requires-Dist: pytest (>=3.4.2) ; extra == 'test'
Requires-Dist: pytest-cov (>=2.6.0) ; extra == 'test'
